odoo/addons/stock_picking_volume_packaging/README.rst
odoo/addons/stock_picking_volume_packaging/__init__.py
odoo/addons/stock_picking_volume_packaging/__manifest__.py
odoo/addons/stock_picking_volume_packaging/i18n/it.po
odoo/addons/stock_picking_volume_packaging/i18n/stock_picking_volume_packaging.pot
odoo/addons/stock_picking_volume_packaging/models/__init__.py
odoo/addons/stock_picking_volume_packaging/models/product_product.py
odoo/addons/stock_picking_volume_packaging/readme/CONTRIBUTORS.md
odoo/addons/stock_picking_volume_packaging/readme/CREDITS.md
odoo/addons/stock_picking_volume_packaging/readme/DESCRIPTION.md
odoo/addons/stock_picking_volume_packaging/readme/USAGE.md
odoo/addons/stock_picking_volume_packaging/static/description/icon.png
odoo/addons/stock_picking_volume_packaging/static/description/index.html
odoo/addons/stock_picking_volume_packaging/tests/__init__.py
odoo/addons/stock_picking_volume_packaging/tests/test_stock_move_volume.py
odoo_addon_stock_picking_volume_packaging-18.0.1.0.0.2.dist-info/METADATA
odoo_addon_stock_picking_volume_packaging-18.0.1.0.0.2.dist-info/WHEEL
odoo_addon_stock_picking_volume_packaging-18.0.1.0.0.2.dist-info/top_level.txt
odoo_addon_stock_picking_volume_packaging-18.0.1.0.0.2.dist-info/RECORD
