Metadata-Version: 2.1
Name: odoo-addon-stock_picking_volume_packaging
Version: 18.0.1.0.0.2
Requires-Python: >=3.10
Requires-Dist: odoo-addon-product_packaging_dimension==18.0.*
Requires-Dist: odoo-addon-stock_packaging_calculator==18.0.*
Requires-Dist: odoo-addon-stock_picking_volume==18.0.*
Requires-Dist: odoo==18.0.*
Summary: Use volume information on potential product packaging to compute the volume of a stock.move
Home-page: https://github.com/OCA/stock-logistics-warehouse
License: AGPL-3
Author: ACSONE SA/NV,Odoo Community Association (OCA)
Author-email: support@odoo-community.org
Classifier: Programming Language :: Python
Classifier: Framework :: Odoo
Classifier: Framework :: Odoo :: 18.0
Classifier: License :: OSI Approved :: GNU Affero General Public License v3
